{"fluffos":{"pinkfish":"%^CYAN%^%^BOLD%^","html":"<SPAN style=\"color: #55ffff\">","channel":"fluffos"},"wotf-devel":{"channel":"wotf-devel","html":"<SPAN style=\"color: #ff55ff\">","pinkfish":"%^MAGENTA%^%^BOLD%^"},"nschat":{"channel":"nschat","html":"<SPAN style=\"color: #55ffff\">","pinkfish":"%^CYAN%^%^BOLD%^"},"smblah":{"channel":"smblah","html":"<SPAN style=\"color: #55ff55\">","pinkfish":"%^GREEN%^%^BOLD%^"},"imud_code":{"channel":"imud_code","html":"<SPAN style=\"color: #bbbb00\">","pinkfish":"%^ORANGE%^"},"inews":{"pinkfish":"%^BLUE%^","html":"<SPAN style=\"color: #0000bb\">","channel":"inews"},"dwchat":{"pinkfish":"%^WHITE%^%^BOLD%^","html":"<SPAN style=\"color: #ffffff\">","channel":"dwchat"},"serenity":{"html":"<SPAN style=\"color: #bbbbbb\">","pinkfish":"%^WHITE%^","channel":"serenity"},"bestiality":{"pinkfish":"%^RED%^%^BOLD%^","html":"<SPAN style=\"color: #ff5555\">","channel":"bestiality"},"rome_chat":{"channel":"rome_chat","pinkfish":"%^RED%^","html":"<SPAN style=\"color: #bb0000\">"},"sport":{"channel":"sport","html":"<SPAN style=\"color: #00bb00\">","pinkfish":"%^GREEN%^"},"discworld-chat":{"channel":"discworld-chat","pinkfish":"%^WHITE%^%^BOLD%^","html":"<SPAN style=\"color: #ffffff\">"},"mudnews":{"channel":"mudnews","pinkfish":"%^WHITE%^%^BOLD%^","html":"<SPAN style=\"color: #ffffff\">"},"igossip":{"channel":"igossip","html":"<SPAN style=\"color: #ff5555\">","pinkfish":"%^RED%^%^BOLD%^"},"dead_souls":{"channel":"dead_souls","pinkfish":"%^ORANGE%^","html":"<SPAN style=\"color: #bbbb00\">"},"trivia_games":{"html":"<SPAN style=\"color: #bbbb00\">","pinkfish":"%^ORANGE%^","channel":"trivia_games"},"icode":{"channel":"icode","pinkfish":"%^GREEN%^","html":"<SPAN style=\"color: #00bb00\">"},"furry":{"channel":"furry","pinkfish":"%^RED%^%^BOLD%^","html":"<SPAN style=\"color: #ff5555\">"},"discworld-cre":{"channel":"discworld-cre","html":"<SPAN style=\"color: #55ff55\">","pinkfish":"%^GREEN%^%^BOLD%^"},"adr":{"pinkfish":"%^BLUE%^%^BOLD%^","html":"<SPAN style=\"color: #5555ff\">","channel":"adr"},"insomnia-chat":{"pinkfish":"%^RED%^%^BOLD%^","html":"<SPAN style=\"color: #ff5555\">","channel":"insomnia-chat"},"linux":{"channel":"linux","pinkfish":"%^BLUE%^%^BOLD%^","html":"<SPAN style=\"color: #5555ff\">"},"dutch":{"channel":"dutch","html":"<SPAN style=\"color: #00bb00\">","pinkfish":"%^GREEN%^"},"discworld_chat":{"channel":"discworld_chat","pinkfish":"%^WHITE%^%^BOLD%^","html":"<SPAN style=\"color: #ffffff\">"},"bd_devtalk":{"channel":"bd_devtalk","html":"<SPAN style=\"color: #0000bb\">","pinkfish":"%^BLUE%^"},"ifree":{"channel":"ifree","pinkfish":"%^WHITE%^%^BOLD%^","html":"<SPAN style=\"color: #ffffff\">"},"coffeemud_universe":{"pinkfish":"%^MAGENTA%^","html":"<SPAN style=\"color: #bb00bb\">","channel":"coffeemud_universe"},"dgd":{"html":"<SPAN style=\"color: #bb00bb\">","pinkfish":"%^MAGENTA%^","channel":"dgd"},"ichat":{"channel":"ichat","pinkfish":"%^ORANGE%^","html":"<SPAN style=\"color: #bbbb00\">"},"ea":{"pinkfish":"%^CYAN%^%^BOLD%^","html":"<SPAN style=\"color: #55ffff\">","channel":"ea"},"crossmud":{"html":"<SPAN style=\"color: #00bbbb\">","pinkfish":"%^CYAN%^","channel":"crossmud"},"cleric":{"channel":"cleric","html":"<SPAN style=\"color: #0000bb\">","pinkfish":"%^BLUE%^"},"german":{"html":"<SPAN style=\"color: #bb0000\">","pinkfish":"%^RED%^","channel":"german"},"ds":{"pinkfish":"%^ORANGE%^","html":"<SPAN style=\"color: #bbbb00\">","channel":"ds"},"mychannel":{"html":"<SPAN style=\"color: #0000bb\">","pinkfish":"%^BLUE%^","channel":"mychannel"},"mlp":{"channel":"mlp","html":"<SPAN style=\"color: #55ff55\">","pinkfish":"%^GREEN%^%^BOLD%^"},"intercre":{"pinkfish":"%^ORANGE%^","html":"<SPAN style=\"color: #bbbb00\">","channel":"intercre"},"ooc":{"channel":"ooc","pinkfish":"%^WHITE%^%^BOLD%^","html":"<SPAN style=\"color: #ffffff\">"},"minecraft":{"channel":"minecraft","pinkfish":"%^YELLOW%^","html":"<SPAN style=\"color: #ffff55\">"},"wiley":{"channel":"wiley","html":"<SPAN style=\"color: #ffff55\">","pinkfish":"%^YELLOW%^"},"crat":{"html":"<SPAN style=\"color: #ff55ff\">","pinkfish":"%^MAGENTA%^%^BOLD%^","channel":"crat"},"%^reset%^":{"pinkfish":"%^CYAN%^","html":"<SPAN style=\"color: #00bbbb\">","channel":"%^reset%^"},"lima":{"pinkfish":"%^MAGENTA%^%^BOLD%^","html":"<SPAN style=\"color: #ff55ff\">","channel":"lima"},"french":{"channel":"french","pinkfish":"%^RED%^","html":"<SPAN style=\"color: #bb0000\">"},"jammstest":{"html":"<SPAN style=\"color: #5555ff\">","pinkfish":"%^BLUE%^%^BOLD%^","channel":"jammstest"},"havenlib":{"pinkfish":"%^BLUE%^","html":"<SPAN style=\"color: #0000bb\">","channel":"havenlib"},"gw_imm":{"channel":"gw_imm","pinkfish":"%^ORANGE%^","html":"<SPAN style=\"color: #bbbb00\">"},"test":{"html":"<SPAN style=\"color: #ff5555\">","pinkfish":"%^RED%^%^BOLD%^","channel":"test"},"1":{"pinkfish":"%^CYAN%^","html":"<SPAN style=\"color: #00bbbb\">","channel":"1"},"dreamverse_gossip":{"channel":"dreamverse_gossip","pinkfish":"%^RED%^","html":"<SPAN style=\"color: #bb0000\">"},"dragon":{"channel":"dragon","html":"<SPAN style=\"color: #bbbbbb\">","pinkfish":"%^WHITE%^"},"dead_test8":{"channel":"dead_test8","html":"<SPAN style=\"color: #55ff55\">","pinkfish":"%^GREEN%^%^BOLD%^"},"troll":{"pinkfish":"%^RED%^","html":"<SPAN style=\"color: #bb0000\">","channel":"troll"},"imud_gossip":{"html":"<SPAN style=\"color: #00bb00\">","pinkfish":"%^GREEN%^","channel":"imud_gossip"},"dead_test4":{"pinkfish":"%^MAGENTA%^","html":"<SPAN style=\"color: #bb00bb\">","channel":"dead_test4"},"otg":{"channel":"otg","html":"<SPAN style=\"color: #ff55ff\">","pinkfish":"%^MAGENTA%^%^BOLD%^"},"zblah":{"html":"<SPAN style=\"color: #ff55ff\">","pinkfish":"%^MAGENTA%^%^BOLD%^","channel":"zblah"},"dwcre":{"pinkfish":"%^BLUE%^","html":"<SPAN style=\"color: #0000bb\">","channel":"dwcre"},"inter-router":{"pinkfish":"%^CYAN%^%^BOLD%^","html":"<SPAN style=\"color: #55ffff\">","channel":"inter-router"},"nscre":{"channel":"nscre","pinkfish":"%^WHITE%^","html":"<SPAN style=\"color: #bbbbbb\">"},"blah":{"channel":"blah","html":"<SPAN style=\"color: #ffff55\">","pinkfish":"%^YELLOW%^"},"free_speech":{"channel":"free_speech","pinkfish":"%^RED%^","html":"<SPAN style=\"color: #bb0000\">"},"pyom":{"channel":"pyom","pinkfish":"%^FLASH%^%^GREEN%^","html":"<SPAN style=\"color: #55ff55\">"},"newbie":{"html":"<SPAN style=\"color: #55ff55\">","pinkfish":"%^GREEN%^%^BOLD%^","channel":"newbie"},"ds_test":{"html":"<SPAN style=\"color: #5555ff\">","pinkfish":"%^BLUE%^%^BOLD%^","channel":"ds_test"},"godwars":{"channel":"godwars","pinkfish":"%^GREEN%^","html":"<SPAN style=\"color: #00bb00\">"},"free_speach":{"pinkfish":"%^YELLOW%^","html":"<SPAN style=\"color: #ffff55\">","channel":"free_speach"},"church":{"channel":"church","html":"<SPAN style=\"color: #bbbb00\">","pinkfish":"%^ORANGE%^"},"wolimm":{"channel":"wolimm","pinkfish":"%^MAGENTA%^","html":"<SPAN style=\"color: #bb00bb\">"},"dchat":{"channel":"dchat","html":"<SPAN style=\"color: #00bbbb\">","pinkfish":"%^CYAN%^"},"url":{"html":"<SPAN style=\"background-color: #0000bb; color: #ffff55\">","pinkfish":"%^YELLOW%^%^B_BLUE%^","channel":"url"},"avatar":{"pinkfish":"%^YELLOW%^","html":"<SPAN style=\"color: #ffff55\">","channel":"avatar"},"bsg":{"channel":"bsg","html":"<SPAN style=\"color: #bb00bb\">","pinkfish":"%^MAGENTA%^"},"ascii_art":{"channel":"ascii_art","pinkfish":"%^YELLOW%^","html":"<SPAN style=\"color: #ffff55\">"},"lpuni":{"channel":"lpuni","html":"<SPAN style=\"color: #bbbbbb\">","pinkfish":"%^WHITE%^"},"wolchat":{"channel":"wolchat","pinkfish":"%^CYAN%^","html":"<SPAN style=\"color: #00bbbb\">"},"4l":{"channel":"4l","pinkfish":"%^WHITE%^%^BOLD%^","html":"<SPAN style=\"color: #ffffff\">"},"imud_sgz":{"channel":"imud_sgz","pinkfish":"%^GREEN%^","html":"<SPAN style=\"color: #00bb00\">"},"wileymud":{"channel":"wileymud","html":"<SPAN style=\"color: #ffff55\">","pinkfish":"%^YELLOW%^"},"public":{"channel":"public","pinkfish":"%^BLUE%^%^BOLD%^","html":"<SPAN style=\"color: #5555ff\">"},"vest":{"channel":"vest","html":"<SPAN style=\"color: #55ffff\">","pinkfish":"%^CYAN%^%^BOLD%^"},"animechat":{"pinkfish":"%^MAGENTA%^","html":"<SPAN style=\"color: #bb00bb\">","channel":"animechat"},"discord":{"channel":"discord","html":"<SPAN style=\"color: #bbbb00\">","pinkfish":"%^ORANGE%^"},"intergossip":{"channel":"intergossip","pinkfish":"%^GREEN%^","html":"<SPAN style=\"color: #00bb00\">"},"bofh":{"channel":"bofh","html":"<SPAN style=\"color: #00bbbb\">","pinkfish":"%^CYAN%^"},"bot":{"html":"<SPAN style=\"color: #bb00bb\">","pinkfish":"%^MAGENTA%^","channel":"bot"},"default-IMC2":{"pinkfish":"%^B_BLUE%^%^WHITE%^","html":"<SPAN style=\"background-color: #0000bb; color: #ffffff\">","channel":"default-IMC2"},"gossip":{"pinkfish":"%^WHITE%^","html":"<SPAN style=\"color: #bbbbbb\">","channel":"gossip"},"default":{"html":"<SPAN style=\"color: #5555ff\">","pinkfish":"%^BLUE%^%^BOLD%^","channel":"default"}}